myfuncs/__init__.py
myfuncs/funcs.py
tests/__init__.py
tests/funcspy_tests.py
tests/main_tests.py
myfuncs-1.1.0.dist-info/LICENSE
myfuncs-1.1.0.dist-info/METADATA
myfuncs-1.1.0.dist-info/WHEEL
myfuncs-1.1.0.dist-info/top_level.txt
myfuncs-1.1.0.dist-info/RECORD
