Metadata-Version: 2.1
Name: myfuncs
Version: 1.1.0
Summary: Personal utility functions that I use across different codebases.
Home-page: https://github.com/cc-d/myfuncs
Author: Cary Carter
Author-email: ccarterdev@gmail.com
License: MIT
Classifier: Development Status :: 3 - Alpha
Classifier: Intended Audience :: Developers
Classifier: License :: OSI Approved :: MIT License
Classifier: Programming Language :: Python :: 3
Classifier: Programming Language :: Python :: 3.6
Classifier: Programming Language :: Python :: 3.7
Classifier: Programming Language :: Python :: 3.8
Classifier: Programming Language :: Python :: 3.9
Classifier: Programming Language :: Python :: 3.10
License-File: LICENSE
Requires-Dist: logfunc (==1.4.1)
